odoo10_addon_hr_public_holidays-10.0.1.3.0-nspkg.pth
odoo/addons/hr_public_holidays/README.rst
odoo/addons/hr_public_holidays/__init__.py
odoo/addons/hr_public_holidays/__manifest__.py
odoo/addons/hr_public_holidays/data/ir_config_parameter.xml
odoo/addons/hr_public_holidays/i18n/ar.po
odoo/addons/hr_public_holidays/i18n/cs_CZ.po
odoo/addons/hr_public_holidays/i18n/de.po
odoo/addons/hr_public_holidays/i18n/es.po
odoo/addons/hr_public_holidays/i18n/fi.po
odoo/addons/hr_public_holidays/i18n/fr.po
odoo/addons/hr_public_holidays/i18n/hr.po
odoo/addons/hr_public_holidays/i18n/hr_HR.po
odoo/addons/hr_public_holidays/i18n/hr_public_holidays.pot
odoo/addons/hr_public_holidays/i18n/it.po
odoo/addons/hr_public_holidays/i18n/lt.po
odoo/addons/hr_public_holidays/i18n/nl_NL.po
odoo/addons/hr_public_holidays/i18n/pl.po
odoo/addons/hr_public_holidays/i18n/pt_BR.po
odoo/addons/hr_public_holidays/i18n/ro.po
odoo/addons/hr_public_holidays/i18n/sl.po
odoo/addons/hr_public_holidays/models/__init__.py
odoo/addons/hr_public_holidays/models/hr_public_holidays.py
odoo/addons/hr_public_holidays/models/hr_public_holidays_line.py
odoo/addons/hr_public_holidays/security/ir.model.access.csv
odoo/addons/hr_public_holidays/static/description/icon.png
odoo/addons/hr_public_holidays/static/description/icon.svg
odoo/addons/hr_public_holidays/static/src/js/holidays_highlighter.js
odoo/addons/hr_public_holidays/templates/assets.xml
odoo/addons/hr_public_holidays/tests/__init__.py
odoo/addons/hr_public_holidays/tests/test_public_holidays.py
odoo/addons/hr_public_holidays/views/hr_public_holidays_view.xml
odoo/addons/hr_public_holidays/wizards/__init__.py
odoo/addons/hr_public_holidays/wizards/public_holidays_next_year_wizard.py
odoo/addons/hr_public_holidays/wizards/public_holidays_next_year_wizard.xml
odoo10_addon_hr_public_holidays-10.0.1.3.0.dist-info/METADATA
odoo10_addon_hr_public_holidays-10.0.1.3.0.dist-info/WHEEL
odoo10_addon_hr_public_holidays-10.0.1.3.0.dist-info/namespace_packages.txt
odoo10_addon_hr_public_holidays-10.0.1.3.0.dist-info/top_level.txt
odoo10_addon_hr_public_holidays-10.0.1.3.0.dist-info/RECORD
